aacc/__init__.py
aacc-2.0.1.dist-info/METADATA
aacc-2.0.1.dist-info/WHEEL
aacc-2.0.1.dist-info/top_level.txt
aacc-2.0.1.dist-info/RECORD
