Metadata-Version: 2.4
Name: aacc
Version: 2.0.1
Summary: Use 'aacc()' instead of 'print()' in Python
Author: Programmer Seo Hook : @LAEGER_MO 
Classifier: Programming Language :: Python :: 3
Classifier: License :: OSI Approved :: MIT License
Classifier: Operating System :: OS Independent
Requires-Python: >=3.0
Dynamic: author
Dynamic: classifier
Dynamic: description
Dynamic: description-content-type
Dynamic: requires-python
Dynamic: summary
